{"datatranferfileurl":"/ARCHIVE/LT1B/LEVEL1A/SAR/2024/0603/12309/415505/LT1B_MONO_KSC_STRIP1_012309_E95.2_N22.4_20240603_SLC_HH_L1A_0000415505.tar.gz","productid":"415505","dataarchivefileurl":"/ARCHIVE/LT1B/LEVEL1A/SAR/2024/0603/12309/415505/LT1B_MONO_KSC_STRIP1_012309_E95.2_N22.4_20240603_SLC_HH_L1A_0000415505.tar.gz","bottomleftlatitude":"22.0833077662","lookdirection":"RIGHT","starttime":"2024-06-03T11:42:06.280410","rxgainsettingtype":"MGC","attitudedataqualitylowflag":"false","dataarchivefile":"LT1B_MONO_KSC_STRIP1_012309_E95.2_N22.4_20240603_SLC_HH_L1A_0000415505.tar.gz","polarisationmode":"HH","rangelooks":"1","bottomrightlongitude":"95.5190804341","quantisationcontrol":"10:6BAQ","orbitid":"12309","satellitemode":"MONOSTATIC","id":"LT1B-SAR-LEVEL1A-415505","columnspacing":"1.66551365555555564E+00","azimuthlooks":"1","azimuthresolution":"2.88431475146992744E+00","missingauxdataflag":"false","numberofcolumns":"19160","isrelease":"TRUE","create_time":"2024-06-03 23:26:26","datastatus":"1","calibrationconst":"7.00000000000000000E+00","bottomleftlongitude":"95.0035961376","metadataid":"LT1B-SAR-LEVEL1A-415505","fromframe":"WGS84","rowspacing":"1.97432689245119342E+00","imagedataformat":"TIFF","elevationbeamconfiguration":"7","pulselength":"9.99999999999999912E-05","sceneid":"412292","pixelvalueid":"SIGMMA","toprightlongitude":"95.4140028953","centerlongitude":"95.2142515808","groundrangeresolution":"3.47299863263529485E+00","flag":"TRUE","satelliteid":"LT1B","producetype":"LEVEL1A","insert_time":"2024-06-03 23:26:26","orbitaccuracy":"RT","centerlatitude":"22.3937401285","orbitdirection":"ASC","topleftlatitude":"22.6126481535","antennareceiveconfiguration":"DRA","centerfrequency":"1.26000000000000000E+09","sensormode":"Master","toprightlatitude":"22.7015950576","demqualitylowflag":"false","numberofrows":"30274","projection":"SLANTRANGE","productlevel":"LEVEL1A","productvariant":"SSC","toframe":"WGS84","pulsebandwidth":"8.00000000000000000E+07","imagingmode":"STRIP1","receivestationid":"KSC","topleftlongitude":"94.8964560644","orbitdataqualitylowflag":"false","pollayer":"HH","bottomrightlatitude":"22.1724095072","endtime":"2024-06-03T11:42:14.865328","relorbit":"60","sensorid":"SAR","imagedatatype":"COMPLEX","time":"2024-06-03 23:26:26","imagedatadepth":"16","producetime":"2024-06-03T23:16:54"}